Workbook

Sheet Dashboard
A1: Bakery Costing & Pricing Template
A2: Professional workbook for ingredient costing, order pricing, delivery and margin control
A4: How to use
A5: 1. Update ingredient purchase prices and package sizes on the Ingredients sheet.
A6: 2. Adjust labor rate, delivery rate and rounding rules on the Setup sheet.
A7: 3. On Order_Costing, choose ingredients from the dropdown and enter quantities used.
A8: 4. Enter packaging, labor hours, delivery distance and any extra overhead.
A9: 5. Use the suggested selling price and rounded quote to price the cake professionally.
A10: 6. Copy key figures into Order_Log to keep a history of quotes and completed jobs.
A13: Workbook structure
A14: Setup | B14: Business assumptions: labor, delivery, default margin, quote rounding
A15: Ingredients | B15: Master list of ingredients with effective cost per base unit
A16: Order_Costing | B16: Pricing calculator for a single cake or order quote
A17: Order_Log | B17: History tracker for quoted / delivered jobs and profit review
A20: Key reminder
A21: Do not price cakes using ingredients alone. Count packaging, delivery, labor, utilities and a proper profit margin. That little monster called underpricing eats bakeries for breakfast.

Sheet Setup
A1: Business Assumptions
A2: Change the blue input cells to match your bakery
A4: Core Pricing Controls
A5: Currency / market note | B5: Update currency formatting manually if needed | C5: Static note
A6: Labor rate per hour | B6: 100 | C6: User input
A7: Delivery rate per km | B7: 3 | C7: User input
A8: Default target margin | B8: 0.35 | C8: User input
A9: Default overhead add-on | B9: 0 | C9: Optional extra charge per order
A10: Quote rounding increment | B10: 50 | C10: Rounds quote up to nearest amount
A13: Tips
A14: Use a realistic labor rate even if you are the one baking. Your time is not fairy dust.
A15: Use delivery per km or replace it with a flat fee if that fits your business better.
A16: Keep your target margin honest. Fancy cakes with intricate decoration usually need more room.

Sheet Ingredients
A1: Ingredients Cost Library
A2: Update purchase sizes and prices; effective cost per base unit calculates automatically
A4: Ingredient | B4: Category | C4: Supplier | D4: Purchase Qty | E4: Base Unit | F4: Package Cost | G4: Waste % | H4: Effective Cost / Unit | I4: Last Updated | J4: Notes
A5: Flour | B5: Dry Goods | C5: Local Wholesale | D5: 1000 | E5: g | F5: 80 | G5: 0 | H5: =IFERROR((F5/D5)*(1+G5),"") -> 0.08 | J5: 1 kg bag
A6: Sugar | B6: Dry Goods | C6: Local Wholesale | D6: 1000 | E6: g | F6: 50 | G6: 0 | H6: =IFERROR((F6/D6)*(1+G6),"") -> 0.05 | J6: 1 kg bag
A7: Butter | B7: Dairy | C7: Grocer | D7: 250 | E7: g | F7: 80 | G7: 0 | H7: =IFERROR((F7/D7)*(1+G7),"") -> 0.32 | J7: 250 g block
A8: Eggs | B8: Dairy | C8: Farm Supplier | D8: 12 | E8: pcs | F8: 115 | G8: 0 | H8: =IFERROR((F8/D8)*(1+G8),"") -> 9.5833333 | J8: Pack of 12
A9: Milk | B9: Dairy | C9: Grocer | D9: 1000 | E9: ml | F9: 245 | G9: 0 | H9: =IFERROR((F9/D9)*(1+G9),"") -> 0.245 | J9: 1 liter
A10: Vanilla Extract | B10: Flavoring | C10: Grocer | D10: 100 | E10: ml | F10: 50 | G10: 0 | H10: =IFERROR((F10/D10)*(1+G10),"") -> 0.5 | J10: Bottle
A11: Whipping Cream | B11: Dairy | C11: Grocer | D11: 500 | E11: ml | F11: 145 | G11: 0 | H11: =IFERROR((F11/D11)*(1+G11),"") -> 0.29 | J11: Carton
A12: Cocoa Powder | B12: Dry Goods | C12: Grocer | D12: 250 | E12: g | F12: 60 | G12: 0 | H12: =IFERROR((F12/D12)*(1+G12),"") -> 0.24 | J12: Pouch
A13: Cream Cheese | B13: Dairy | C13: Grocer | D13: 250 | E13: g | F13: 150 | G13: 0 | H13: =IFERROR((F13/D13)*(1+G13),"") -> 0.6 | J13: Tub
A14: Fondant | B14: Decor | C14: Cake Supply | D14: 1000 | E14: g | F14: 75 | G14: 0 | H14: =IFERROR((F14/D14)*(1+G14),"") -> 0.075 | J14: 1 kg pack
H15: =IFERROR((F15/D15)*(1+G15),"")
H16: =IFERROR((F16/D16)*(1+G16),"")
H17: =IFERROR((F17/D17)*(1+G17),"")
H18: =IFERROR((F18/D18)*(1+G18),"")
H19: =IFERROR((F19/D19)*(1+G19),"")
H20: =IFERROR((F20/D20)*(1+G20),"")
H21: =IFERROR((F21/D21)*(1+G21),"")
H22: =IFERROR((F22/D22)*(1+G22),"")
H23: =IFERROR((F23/D23)*(1+G23),"")
H24: =IFERROR((F24/D24)*(1+G24),"")
H25: =IFERROR((F25/D25)*(1+G25),"")
H26: =IFERROR((F26/D26)*(1+G26),"")
... H204: =IFERROR((F204/D204)*(1+G204),"")

Sheet Order_Costing
A1: Order Costing & Quote Builder
A2: Use dropdowns to build one cake quote at a time
A4: Order Details
A5: Order ID | B5: Q-001 | D5: Customer | E5: Rahul
A6: Order Date | D6: Product / Cake | E6: Napoliten – Eid
A7: Quantity | B7: 5 | D7: Delivery Status | E7: Delivery
A9: Pricing Inputs
A10: Packaging Cost | B10: 20 | C10: Labor Hours | D10: 2 | E10: Delivery Distance (km) | F10: 15 | G10: Actual Selling Price | H10: 1500
A11: Extra Overhead | B11: =Setup!B9 -> 0 | C11: Target Margin | D11: =Setup!B8 -> 0.35
A13: Ingredients Used | J13: Quote Summary
A14: Line | B14: Ingredient | C14: Unit | D14: Qty Used | E14: Unit Cost | F14: Line Cost | G14: Notes
A15: 1 | B15: Flour | C15: =IFERROR(VLOOKUP(B15,Ingredients!$A$5:$H$204,5,FALSE()),"") -> g | D15: 500 | E15: =IFERROR(VLOOKUP(B15,Ingredients!$A$5:$H$204,8,FALSE()),"") -> 0.08 | F15: =IF(OR(B15="",D15=""),"",D15*E15*$B$7) -> 200 | K15: Ingredient Subtotal | L15: =SUM(F15:F39) -> 1812.5
A16: 2 | B16: Milk | C16: =IFERROR(VLOOKUP(B16,Ingredients!$A$5:$H$204,5,FALSE()),"") -> ml | D16: 500 | E16: =IFERROR(VLOOKUP(B16,Ingredients!$A$5:$H$204,8,FALSE()),"") -> 0.245 | F16: =IF(OR(B16="",D16=""),"",D16*E16*$B$7) -> 612.5 | K16: Packaging | L16: =B10 -> 20
A17: 3 | B17: Eggs | C17: =IFERROR(VLOOKUP(B17,Ingredients!$A$5:$H$204,5,FALSE()),"") -> pcs | D17: 12 | E17: =IFERROR(VLOOKUP(B17,Ingredients!$A$5:$H$204,8,FALSE()),"") -> 9.5833333 | F17: =IF(OR(B17="",D17=""),"",D17*E17*$B$7) -> 575 | K17: Labor Cost | L17: =D10*Setup!B6 -> 200
A18: 4 | B18: Vanilla Extract | C18: =IFERROR(VLOOKUP(B18,Ingredients!$A$5:$H$204,5,FALSE()),"") -> ml | D18: 50 | E18: =IFERROR(VLOOKUP(B18,Ingredients!$A$5:$H$204,8,FALSE()),"") -> 0.5 | F18: =IF(OR(B18="",D18=""),"",D18*E18*$B$7) -> 125 | K18: Delivery Cost | L18: =F10*Setup!B7 -> 45
A19: 5 | B19: Cream Cheese | C19: =IFERROR(VLOOKUP(B19,Ingredients!$A$5:$H$204,5,FALSE()),"") -> g | D19: 100 | E19: =IFERROR(VLOOKUP(B19,Ingredients!$A$5:$H$204,8,FALSE()),"") -> 0.6 | F19: =IF(OR(B19="",D19=""),"",D19*E19*$B$7) -> 300 | K19: Extra Overhead | L19: =B11 -> 0
A20: 6 | C20: =IFERROR(VLOOKUP(B20,Ingredients!$A$5:$H$204,5,FALSE()),"") | E20: =IFERROR(VLOOKUP(B20,Ingredients!$A$5:$H$204,8,FALSE()),"") | F20: =IF(OR(B20="",D20=""),"",D20*E20*$B$7) | K20: Total Cost | L20: =SUM(L15:L19) -> 2077.5
A21: 7 | C21: =IFERROR(VLOOKUP(B21,Ingredients!$A$5:$H$204,5,FALSE()),"") | E21: =IFERROR(VLOOKUP(B21,Ingredients!$A$5:$H$204,8,FALSE()),"") | F21: =IF(OR(B21="",D21=""),"",D21*E21*$B$7) | K21: Target Margin | L21: =D11 -> 0.35
A22: 8 | C22: =IFERROR(VLOOKUP(B22,Ingredients!$A$5:$H$204,5,FALSE()),"") | E22: =IFERROR(VLOOKUP(B22,Ingredients!$A$5:$H$204,8,FALSE()),"") | F22: =IF(OR(B22="",D22=""),"",D22*E22*$B$7) | K22: Suggested Price | L22: =IF(L20="","",L20/(1-L21)) -> 3196.1538
A23: 9 | C23: =IFERROR(VLOOKUP(B23,Ingredients!$A$5:$H$204,5,FALSE()),"") | E23: =IFERROR(VLOOKUP(B23,Ingredients!$A$5:$H$204,8,FALSE()),"") | F23: =IF(OR(B23="",D23=""),"",D23*E23*$B$7) | K23: Rounded Quote | L23: =IF(L22="","",ROUNDUP(L22/Setup!B10,0)*Setup!B10) -> 3200
A24: 10 | C24: =IFERROR(VLOOKUP(B24,Ingredients!$A$5:$H$204,5,FALSE()),"") | E24: =IFERROR(VLOOKUP(B24,Ingredients!$A$5:$H$204,8,FALSE()),"") | F24: =IF(OR(B24="",D24=""),"",D24*E24*$B$7) | K24: Profit @ Actual Sell | L24: =IF(H10="","",H10-L20) -> -577.5
A25: 11 | C25: =IFERROR(VLOOKUP(B25,Ingredients!$A$5:$H$204,5,FALSE()),"") | E25: =IFERROR(VLOOKUP(B25,Ingredients!$A$5:$H$204,8,FALSE()),"") | F25: =IF(OR(B25="",D25=""),"",D25*E25*$B$7) | K25: Margin @ Actual Sell | L25: =IF(H10="","",IF(H10>0,L24/H10,"")) -> -0.385
A26: 12 | C26: =IFERROR(VLOOKUP(B26,Ingredients!$A$5:$H$204,5,FALSE()),"") | E26: =IFERROR(VLOOKUP(B26,Ingredients!$A$5:$H$204,8,FALSE()),"") | F26: =IF(OR(B26="",D26=""),"",D26*E26*$B$7)
A27: 13 | C27: =IFERROR(VLOOKUP(B27,Ingredients!$A$5:$H$204,5,FALSE()),"") | E27: =IFERROR(VLOOKUP(B27,Ingredients!$A$5:$H$204,8,FALSE()),"") | F27: =IF(OR(B27="",D27=""),"",D27*E27*$B$7) | J27: Blue cells = inputs. Black cells = formulas. Use base units consistently: grams, ml, or pcs. If the rounded quote feels scary, that is just math doing cardio.
A28: 14 | C28: =IFERROR(VLOOKUP(B28,Ingredients!$A$5:$H$204,5,FALSE()),"") | E28: =IFERROR(VLOOKUP(B28,Ingredients!$A$5:$H$204,8,FALSE()),"") | F28: =IF(OR(B28="",D28=""),"",D28*E28*$B$7)
A29: 15 | C29: =IFERROR(VLOOKUP(B29,Ingredients!$A$5:$H$204,5,FALSE()),"") | E29: =IFERROR(VLOOKUP(B29,Ingredients!$A$5:$H$204,8,FALSE()),"") | F29: =IF(OR(B29="",D29=""),"",D29*E29*$B$7)
A30: 16 | C30: =IFERROR(VLOOKUP(B30,Ingredients!$A$5:$H$204,5,FALSE()),"") | E30: =IFERROR(VLOOKUP(B30,Ingredients!$A$5:$H$204,8,FALSE()),"") | F30: =IF(OR(B30="",D30=""),"",D30*E30*$B$7)
A31: 17 | C31: =IFERROR(VLOOKUP(B31,Ingredients!$A$5:$H$204,5,FALSE()),"") | E31: =IFERROR(VLOOKUP(B31,Ingredients!$A$5:$H$204,8,FALSE()),"") | F31: =IF(OR(B31="",D31=""),"",D31*E31*$B$7)
A32: 18 | C32: =IFERROR(VLOOKUP(B32,Ingredients!$A$5:$H$204,5,FALSE()),"") | E32: =IFERROR(VLOOKUP(B32,Ingredients!$A$5:$H$204,8,FALSE()),"") | F32: =IF(OR(B32="",D32=""),"",D32*E32*$B$7)
A33: 19 | C33: =IFERROR(VLOOKUP(B33,Ingredients!$A$5:$H$204,5,FALSE()),"") | E33: =IFERROR(VLOOKUP(B33,Ingredients!$A$5:$H$204,8,FALSE()),"") | F33: =IF(OR(B33="",D33=""),"",D33*E33*$B$7)
A34: 20 | C34: =IFERROR(VLOOKUP(B34,Ingredients!$A$5:$H$204,5,FALSE()),"") | E34: =IFERROR(VLOOKUP(B34,Ingredients!$A$5:$H$204,8,FALSE()),"") | F34: =IF(OR(B34="",D34=""),"",D34*E34*$B$7)
A35: 21 | C35: =IFERROR(VLOOKUP(B35,Ingredients!$A$5:$H$204,5,FALSE()),"") | E35: =IFERROR(VLOOKUP(B35,Ingredients!$A$5:$H$204,8,FALSE()),"") | F35: =IF(OR(B35="",D35=""),"",D35*E35*$B$7)
A36: 22 | C36: =IFERROR(VLOOKUP(B36,Ingredients!$A$5:$H$204,5,FALSE()),"") | E36: =IFERROR(VLOOKUP(B36,Ingredients!$A$5:$H$204,8,FALSE()),"") | F36: =IF(OR(B36="",D36=""),"",D36*E36*$B$7)
A37: 23 | C37: =IFERROR(VLOOKUP(B37,Ingredients!$A$5:$H$204,5,FALSE()),"") | E37: =IFERROR(VLOOKUP(B37,Ingredients!$A$5:$H$204,8,FALSE()),"") | F37: =IF(OR(B37="",D37=""),"",D37*E37*$B$7)
A38: 24 | C38: =IFERROR(VLOOKUP(B38,Ingredients!$A$5:$H$204,5,FALSE()),"") | E38: =IFERROR(VLOOKUP(B38,Ingredients!$A$5:$H$204,8,FALSE()),"") | F38: =IF(OR(B38="",D38=""),"",D38*E38*$B$7)
A39: 25 | C39: =IFERROR(VLOOKUP(B39,Ingredients!$A$5:$H$204,5,FALSE()),"") | E39: =IFERROR(VLOOKUP(B39,Ingredients!$A$5:$H$204,8,FALSE()),"") | F39: =IF(OR(B39="",D39=""),"",D39*E39*$B$7)

Sheet Order_Log
A1: Order Log
A2: Record completed quotes and compare estimated cost vs final price
A4: Date | B4: Order ID | C4: Customer | D4: Product | E4: Qty | F4: Estimated Cost | G4: Quoted Price | H4: Final Price | I4: Profit | J4: Margin % | K4: Status | L4: Notes
A5: =TODAY() -> 46089 | B5: =Order_Costing!B5 -> Q-001 | C5: =Order_Costing!E5 -> Rahul | D5: =Order_Costing!E6 -> Napoliten – Eid | E5: =Order_Costing!B7 -> 5 | F5: =Order_Costing!L20 -> 2077.5 | G5: =Order_Costing!L23 -> 3200 | H5: =Order_Costing!H10 -> 1500 | I5: =IF(H5="","",H5-F5) -> -577.5 | J5: =IF(H5="","",IF(H5>0,I5/H5,"")) -> -0.385 | K5: In Progress | L5: Copy this row, paste values to next row to archive the order
I6: =IF(H6="","",H6-F6) | J6: =IF(H6="","",IF(H6>0,I6/H6,""))
I7: =IF(H7="","",H7-F7) | J7: =IF(H7="","",IF(H7>0,I7/H7,""))
I8: =IF(H8="","",H8-F8) | J8: =IF(H8="","",IF(H8>0,I8/H8,""))
I9: =IF(H9="","",H9-F9) | J9: =IF(H9="","",IF(H9>0,I9/H9,""))
I10: =IF(H10="","",H10-F10) | J10: =IF(H10="","",IF(H10>0,I10/H10,""))
I11: =IF(H11="","",H11-F11) | J11: =IF(H11="","",IF(H11>0,I11/H11,""))
I12: =IF(H12="","",H12-F12) | J12: =IF(H12="","",IF(H12>0,I12/H12,""))
I13: =IF(H13="","",H13-F13) | J13: =IF(H13="","",IF(H13>0,I13/H13,""))
I14: =IF(H14="","",H14-F14) | J14: =IF(H14="","",IF(H14>0,I14/H14,""))
I15: =IF(H15="","",H15-F15) | J15: =IF(H15="","",IF(H15>0,I15/H15,""))
I16: =IF(H16="","",H16-F16) | J16: =IF(H16="","",IF(H16>0,I16/H16,""))
I17: =IF(H17="","",H17-F17) | J17: =IF(H17="","",IF(H17>0,I17/H17,""))
... I154: =IF(H154="","",H154-F154) | J154: =IF(H154="","",IF(H154>0,I154/H154,""))
